nteu_translation_engine_fake/__init__.py
nteu_translation_engine_fake/nteu_translation_engine_fake.py
nteu_translation_engine_fake/translate.py
nteu_translation_engine_fake-2.0.0.dist-info/METADATA
nteu_translation_engine_fake-2.0.0.dist-info/WHEEL
nteu_translation_engine_fake-2.0.0.dist-info/top_level.txt
nteu_translation_engine_fake-2.0.0.dist-info/RECORD
