Metadata-Version: 2.1
Name: nteu-translation-engine-fake
Version: 2.0.0
Summary: NTEU engine
Home-page: https://github.com/Pangeamt/nteu_translation_engine_fake
Author: PangeaMT
Author-email: a.cerda@pangeanic.es
License: MIT
Platform: UNKNOWN
